ultra_pass_sidecar/__init__.py
ultra_pass_sidecar/auth_service.py
ultra_pass_sidecar/cli.py
ultra_pass_sidecar/publish.py
ultra_paas_sidecar-0.1.11.dist-info/METADATA
ultra_paas_sidecar-0.1.11.dist-info/WHEEL
ultra_paas_sidecar-0.1.11.dist-info/entry_points.txt
ultra_paas_sidecar-0.1.11.dist-info/top_level.txt
ultra_paas_sidecar-0.1.11.dist-info/RECORD
