Metadata-Version: 2.4
Name: ultra-paas-sidecar
Version: 0.1.11
Summary: 一个简洁的Python微服务sidecar，支持自动注册到Nacos和Feign风格调用，支持配置中心，支持权限，资源管理
Home-page: https://github.com/yourusername/ultra-paas-py-sidecar
Author: Luozhiguo
Author-email: luozhiguo@example.com
License: MIT
Project-URL: Bug Reports, https://github.com/yourusername/ultra-paas-py-sidecar/issues
Project-URL: Source, https://github.com/yourusername/ultra-paas-py-sidecar
Project-URL: Documentation, https://github.com/yourusername/ultra-paas-py-sidecar#readme
Keywords: microservice,sidecar,nacos,service-discovery,feign,flask,fastapi,async,http-client,configuration
Classifier: Development Status :: 4 - Beta
Classifier: Intended Audience :: Developers
Classifier: License :: OSI Approved :: MIT License
Classifier: Operating System :: OS Independent
Classifier: Programming Language :: Python :: 3
Classifier: Programming Language :: Python :: 3.8
Classifier: Programming Language :: Python :: 3.9
Classifier: Programming Language :: Python :: 3.10
Classifier: Programming Language :: Python :: 3.11
Classifier: Programming Language :: Python :: 3.12
Classifier: Topic :: Software Development :: Libraries :: Python Modules
Classifier: Topic :: Internet :: WWW/HTTP :: HTTP Servers
Classifier: Topic :: System :: Distributed Computing
Classifier: Framework :: Flask
Classifier: Framework :: FastAPI
Requires-Python: >=3.8
Requires-Dist: pyyaml<7.0.0,>=5.1
Requires-Dist: aiohttp<4.0.0,>=3.8.0
Requires-Dist: nacos-sdk-python>=1.0.0
Requires-Dist: fastapi<1.0.0,>=0.100.0
Requires-Dist: flask<3.0.0,>=2.0.0
Requires-Dist: flask-cors<5.0.0,>=3.0.0
Requires-Dist: uvicorn<1.0.0,>=0.15.0
Provides-Extra: dev
Requires-Dist: pytest>=6.0; extra == "dev"
Requires-Dist: pytest-asyncio>=0.18.0; extra == "dev"
Requires-Dist: pytest-cov>=3.0.0; extra == "dev"
Requires-Dist: pytest-mock>=3.6.0; extra == "dev"
Requires-Dist: black>=22.0; extra == "dev"
Requires-Dist: flake8>=4.0; extra == "dev"
Requires-Dist: mypy>=0.950; extra == "dev"
Requires-Dist: isort>=5.10.0; extra == "dev"
Requires-Dist: pre-commit>=2.17.0; extra == "dev"
Provides-Extra: test
Requires-Dist: pytest>=6.0; extra == "test"
Requires-Dist: pytest-asyncio>=0.18.0; extra == "test"
Requires-Dist: pytest-cov>=3.0.0; extra == "test"
Requires-Dist: pytest-mock>=3.6.0; extra == "test"
Requires-Dist: responses>=0.20.0; extra == "test"
Provides-Extra: docs
Requires-Dist: sphinx>=4.0.0; extra == "docs"
Requires-Dist: sphinx-rtd-theme>=1.0.0; extra == "docs"
Requires-Dist: myst-parser>=0.17.0; extra == "docs"
Dynamic: author
Dynamic: author-email
Dynamic: classifier
Dynamic: description
Dynamic: description-content-type
Dynamic: home-page
Dynamic: keywords
Dynamic: license
Dynamic: project-url
Dynamic: provides-extra
Dynamic: requires-dist
Dynamic: requires-python
Dynamic: summary
